nonebot_plugin_mypower/__init__.py
nonebot_plugin_mypower/万圣节/1.png
nonebot_plugin_mypower/万圣节/10.png
nonebot_plugin_mypower/万圣节/11.png
nonebot_plugin_mypower/万圣节/12.png
nonebot_plugin_mypower/万圣节/13.png
nonebot_plugin_mypower/万圣节/14.png
nonebot_plugin_mypower/万圣节/15.png
nonebot_plugin_mypower/万圣节/2.png
nonebot_plugin_mypower/万圣节/3.png
nonebot_plugin_mypower/万圣节/4.png
nonebot_plugin_mypower/万圣节/5.png
nonebot_plugin_mypower/万圣节/6.png
nonebot_plugin_mypower/万圣节/7.png
nonebot_plugin_mypower/万圣节/8.png
nonebot_plugin_mypower/万圣节/9.png
nonebot_plugin_mypower/主义/1.png
nonebot_plugin_mypower/主义/10.png
nonebot_plugin_mypower/主义/11.png
nonebot_plugin_mypower/主义/12.png
nonebot_plugin_mypower/主义/13.png
nonebot_plugin_mypower/主义/14.png
nonebot_plugin_mypower/主义/15.png
nonebot_plugin_mypower/主义/16.png
nonebot_plugin_mypower/主义/17.png
nonebot_plugin_mypower/主义/18.png
nonebot_plugin_mypower/主义/19.png
nonebot_plugin_mypower/主义/2.png
nonebot_plugin_mypower/主义/20.png
nonebot_plugin_mypower/主义/21.png
nonebot_plugin_mypower/主义/22.png
nonebot_plugin_mypower/主义/23.png
nonebot_plugin_mypower/主义/3.png
nonebot_plugin_mypower/主义/4.png
nonebot_plugin_mypower/主义/5.png
nonebot_plugin_mypower/主义/6.png
nonebot_plugin_mypower/主义/7.png
nonebot_plugin_mypower/主义/8.png
nonebot_plugin_mypower/主义/9.png
nonebot_plugin_mypower/但是/1.png
nonebot_plugin_mypower/但是/10.png
nonebot_plugin_mypower/但是/11.png
nonebot_plugin_mypower/但是/12.png
nonebot_plugin_mypower/但是/13.png
nonebot_plugin_mypower/但是/14.png
nonebot_plugin_mypower/但是/15.png
nonebot_plugin_mypower/但是/16.png
nonebot_plugin_mypower/但是/17.png
nonebot_plugin_mypower/但是/18.png
nonebot_plugin_mypower/但是/19.png
nonebot_plugin_mypower/但是/2.png
nonebot_plugin_mypower/但是/20.png
nonebot_plugin_mypower/但是/21.png
nonebot_plugin_mypower/但是/22.png
nonebot_plugin_mypower/但是/23.png
nonebot_plugin_mypower/但是/24.png
nonebot_plugin_mypower/但是/25.png
nonebot_plugin_mypower/但是/26.png
nonebot_plugin_mypower/但是/27.png
nonebot_plugin_mypower/但是/28.png
nonebot_plugin_mypower-0.1.6.dist-info/LICENSE
nonebot_plugin_mypower-0.1.6.dist-info/METADATA
nonebot_plugin_mypower-0.1.6.dist-info/WHEEL
nonebot_plugin_mypower-0.1.6.dist-info/RECORD
