Metadata-Version: 2.1
Name: nonebot-plugin-mypower
Version: 0.1.6
Summary: 一款随机生成超能力的插件（适用于Onebot V11）
Home-page: https://github.com/tianyisama/nonebot_plugin_mypower
License: MIT
Author: TianYi
Requires-Python: >=3.8,<4.0
Classifier: License :: OSI Approved :: MIT License
Classifier: Programming Language :: Python :: 3
Classifier: Programming Language :: Python :: 3.8
Classifier: Programming Language :: Python :: 3.9
Classifier: Programming Language :: Python :: 3.10
Classifier: Programming Language :: Python :: 3.11
Classifier: Programming Language :: Python :: 3.12
Requires-Dist: nonebot-adapter-onebot (>=2.1.1,<3.0.0)
Requires-Dist: nonebot2 (>=2.0.0rc1,<3.0.0)
Project-URL: Repository, https://github.com/tianyisama/nonebot_plugin_mypower
